py4vasp/__init__.py
py4vasp/_analysis/mlff.py
py4vasp/_calculations.py
py4vasp/_combine/base.py
py4vasp/_combine/energies.py
py4vasp/_combine/forces.py
py4vasp/_combine/stresses.py
py4vasp/_config.py
py4vasp/_control/__init__.py
py4vasp/_control/base.py
py4vasp/_control/incar.py
py4vasp/_control/kpoints.py
py4vasp/_control/poscar.py
py4vasp/_raw/access.py
py4vasp/_raw/data.py
py4vasp/_raw/data_wrapper.py
py4vasp/_raw/definition.py
py4vasp/_raw/schema.py
py4vasp/_third_party/__init__.py
py4vasp/_third_party/graph/__init__.py
py4vasp/_third_party/graph/contour.py
py4vasp/_third_party/graph/graph.py
py4vasp/_third_party/graph/mixin.py
py4vasp/_third_party/graph/plot.py
py4vasp/_third_party/graph/series.py
py4vasp/_third_party/graph/trace.py
py4vasp/_third_party/interactive.py
py4vasp/_third_party/view/__init__.py
py4vasp/_third_party/view/mixin.py
py4vasp/_third_party/view/view.py
py4vasp/_util/check.py
py4vasp/_util/convert.py
py4vasp/_util/documentation.py
py4vasp/_util/import_.py
py4vasp/_util/index.py
py4vasp/_util/parser.py
py4vasp/_util/reader.py
py4vasp/_util/select.py
py4vasp/_util/slicing.py
py4vasp/calculation/_CONTCAR.py
py4vasp/calculation/__init__.py
py4vasp/calculation/_band.py
py4vasp/calculation/_bandgap.py
py4vasp/calculation/_base.py
py4vasp/calculation/_born_effective_charge.py
py4vasp/calculation/_class.py
py4vasp/calculation/_density.py
py4vasp/calculation/_dielectric_function.py
py4vasp/calculation/_dielectric_tensor.py
py4vasp/calculation/_dispersion.py
py4vasp/calculation/_dos.py
py4vasp/calculation/_elastic_modulus.py
py4vasp/calculation/_electronic_minimization.py
py4vasp/calculation/_energy.py
py4vasp/calculation/_fatband.py
py4vasp/calculation/_force.py
py4vasp/calculation/_force_constant.py
py4vasp/calculation/_internal_strain.py
py4vasp/calculation/_kpoint.py
py4vasp/calculation/_magnetism.py
py4vasp/calculation/_pair_correlation.py
py4vasp/calculation/_partial_charge.py
py4vasp/calculation/_phonon.py
py4vasp/calculation/_phonon_band.py
py4vasp-0.10.4.dist-info/METADATA
py4vasp-0.10.4.dist-info/WHEEL
py4vasp-0.10.4.dist-info/entry_points.txt
py4vasp-0.10.4.dist-info/licenses/LICENSE.txt
py4vasp-0.10.4.dist-info/RECORD
