Metadata-Version: 2.4
Name: py4vasp
Version: 0.10.4
Summary: Tool for assisting with the analysis and setup of VASP calculations.
License: Apache-2.0
License-File: LICENSE.txt
Author: VASP Software GmbH
Author-email: py4vasp@vasp.at
Requires-Python: >=3.9
Classifier: License :: OSI Approved :: Apache Software License
Classifier: Programming Language :: Python :: 3
Classifier: Programming Language :: Python :: 3.9
Classifier: Programming Language :: Python :: 3.10
Classifier: Programming Language :: Python :: 3.11
Classifier: Programming Language :: Python :: 3.12
Classifier: Programming Language :: Python :: 3.13
Classifier: Programming Language :: Python :: 3.14
Requires-Dist: ase (>=3.22.1,!=3.25.0)
Requires-Dist: h5py (>=3.7.0)
Requires-Dist: ipython (>=8.12)
Requires-Dist: kaleido (>=0.2.1,!=0.2.1.post1)
Requires-Dist: nglview (>=3.0.5)
Requires-Dist: numpy (>=1.23)
Requires-Dist: pandas (>=1.4.3)
Requires-Dist: plotly (>=5.9.0)
Requires-Dist: scipy (>=1.12.0)
Project-URL: Homepage, https://vasp.at/py4vasp/latest
Project-URL: Repository, https://github.com/vasp-dev/py4vasp
Project-URL: Support Forum, https://vasp.at/forum/
